robotpywrapper/__init__.py
robotpywrapper/robotpy.py
robotpy_wrapper-0.2.3.dist-info/LICENSE
robotpy_wrapper-0.2.3.dist-info/METADATA
robotpy_wrapper-0.2.3.dist-info/WHEEL
robotpy_wrapper-0.2.3.dist-info/entry_points.txt
robotpy_wrapper-0.2.3.dist-info/top_level.txt
robotpy_wrapper-0.2.3.dist-info/RECORD
