Metadata-Version: 2.1
Name: robotpy-wrapper
Version: 0.2.3
Summary: A wrapper for the common functions of the robotpy package
Author-email: Kellen Watt <kellen@wattsoft.dev>
Classifier: Intended Audience :: Developers
Classifier: Programming Language :: Python :: 3
Classifier: License :: OSI Approved :: BSD License
Classifier: Operating System :: OS Independent
Classifier: Framework :: Robot Framework :: Library
Requires-Python: >=3.8
License-File: LICENSE
Requires-Dist: robotpy
Requires-Dist: robotpy-installer
